stapel/__init__.py
stapel-0.1.0.dist-info/entry_points.txt
stapel-0.1.0.dist-info/LICENSE
stapel-0.1.0.dist-info/WHEEL
stapel-0.1.0.dist-info/METADATA
stapel-0.1.0.dist-info/RECORD
