Metadata-Version: 2.1
Name: stapel
Version: 0.1.0
Summary: Manage IRC logs and statistics.
Home-page: https://github.com/supakeen/stapel
License: MIT
Keywords: statistics,irc
Author: supakeen
Author-email: cmdr@supakeen.com
Requires-Python: >=3.6,<4
Classifier: License :: OSI Approved :: MIT License
Classifier: Programming Language :: Python
Classifier: Programming Language :: Python :: 3
Classifier: Programming Language :: Python :: 3.6
Classifier: Programming Language :: Python :: 3.7
Classifier: Programming Language :: Python :: 3.8
Requires-Dist: click (>=7.0,<8.0)
Requires-Dist: docutils (>=0.16,<0.17)
Requires-Dist: toml (>=0.10.0,<0.11.0)
Project-URL: Repository, https://github.com/supakeen/stapel
